PasswordCardGenerator/CONSOLA.TTF
PasswordCardGenerator/Extras.py
PasswordCardGenerator/Extras.pyi
PasswordCardGenerator/PasswordCardGenerator.py
PasswordCardGenerator/PasswordCardGenerator.pyi
PasswordCardGenerator/__init__.py
PasswordCardGenerator/__init__.pyi
PasswordCardGenerator/__main__.py
PasswordCardGenerator/__main__.pyi
PasswordCardGenerator/GUI/__main__.py
PasswordCardGenerator/GUI/gui.py
PasswordCardGenerator/GUI/assets/img/Logo.png
PasswordCardGenerator/GUI/assets/tmp/dont_delete.dd
PasswordCardGenerator-1.5.1.dist-info/LICENSE
PasswordCardGenerator-1.5.1.dist-info/METADATA
PasswordCardGenerator-1.5.1.dist-info/WHEEL
PasswordCardGenerator-1.5.1.dist-info/top_level.txt
PasswordCardGenerator-1.5.1.dist-info/RECORD
