Metadata-Version: 2.1
Name: PasswordCardGenerator
Version: 1.5.1
Summary: A Password Card Generator
Author: DerSchinken
Maintainer: DerSchinken
Project-URL: Homepage, http://index12.bplaced.net/
Project-URL: Github, https://github.com/DerSchinken/PasswordCardGenerator
Classifier: Intended Audience :: Developers
Classifier: Intended Audience :: System Administrators
Classifier: Intended Audience :: Information Technology
Classifier: Programming Language :: Python :: 3.6
Classifier: Programming Language :: Python :: 3.7
Classifier: Programming Language :: Python :: 3.8
Classifier: Programming Language :: Python :: 3.9
Classifier: Programming Language :: Python :: 3.10
Requires-Python: >= 3.6
License-File: LICENSE
Requires-Dist: pillow ~=8.3.1
Requires-Dist: tabulate ~=0.8.9
Requires-Dist: flask ~=2.0.1
